{
  "tag": "section",
  "classes": "newBanner border ",
  "id": "template--18069017755713__section_new_banner_mTKpMT",
  "styles": {
    "fontSize": "16px",
    "fontWeight": "400",
    "fontFamily": "Avenir, sans-serif",
    "color": "rgb(35, 31, 32)",
    "backgroundColor": "rgb(240, 242, 255)",
    "background": "rgb(240, 242, 255) none repeat scroll 0% 0% / auto padding-box border-box",
    "padding": "20px",
    "paddingTop": "20px",
    "paddingRight": "20px",
    "paddingBottom": "20px",
    "paddingLeft": "20px",
    "width": "1440px",
    "height": "293.422px",
    "display": "block",
    "flexDirection": "row",
    "borderRadius": "12px",
    "border": "3px solid rgb(227, 224, 253)",
    "overflow": "visible",
    "position": "static",
    "opacity": "1",
    "transition": "all",
    "objectFit": "fill",
    "backgroundPosition": "0% 0%"
  },
  "childCount": 1,
  "children": [
    {
      "tag": "div",
      "classes": "newBannerInner",
      "styles": {
        "fontSize": "16px",
        "fontWeight": "400",
        "fontFamily": "Avenir, sans-serif",
        "color": "rgb(35, 31, 32)",
        "background": "rgba(0, 0, 0, 0) none repeat scroll 0% 0% / auto padding-box border-box",
        "margin": "0px 97px",
        "marginRight": "97px",
        "marginLeft": "97px",
        "width": "1200px",
        "height": "247.422px",
        "maxWidth": "1200px",
        "display": "block",
        "flexDirection": "row",
        "border": "0px none rgb(35, 31, 32)",
        "overflow": "visible",
        "position": "static",
        "opacity": "1",
        "transition": "all",
        "objectFit": "fill",
        "backgroundPosition": "0% 0%"
      },
      "childCount": 1,
      "children": [
        {
          "tag": "div",
          "classes": "newBannerSwiper swiper swiper-initialized swiper-horizontal swiper-backface-hidden",
          "styles": {
            "fontSize": "16px",
            "fontWeight": "400",
            "fontFamily": "Avenir, sans-serif",
            "color": "rgb(35, 31, 32)",
            "background": "rgba(0, 0, 0, 0) none repeat scroll 0% 0% / auto padding-box border-box",
            "width": "1200px",
            "height": "247.422px",
            "display": "block",
            "flexDirection": "row",
            "border": "0px none rgb(35, 31, 32)",
            "overflow": "hidden",
            "position": "relative",
            "zIndex": "1",
            "opacity": "1",
            "transition": "all",
            "objectFit": "fill",
            "backgroundPosition": "0% 0%"
          },
          "childCount": 5,
          "children": [
            {
              "tag": "div",
              "classes": "swiper-wrapper",
              "id": "swiper-wrapper-c78e2bc4c7e1d4fc",
              "styles": {
                "fontSize": "16px",
                "fontWeight": "400",
                "fontFamily": "Avenir, sans-serif",
                "color": "rgb(35, 31, 32)",
                "background": "rgba(0, 0, 0, 0) none repeat scroll 0% 0% / auto padding-box border-box",
                "width": "1200px",
                "height": "200.422px",
                "display": "flex",
                "flexDirection": "row",
                "alignItems": "center",
                "border": "0px none rgb(35, 31, 32)",
                "overflow": "visible",
                "position": "relative",
                "zIndex": "1",
                "opacity": "1",
                "transform": "matrix(1, 0, 0, 1, 0, 0)",
                "transition": "transform",
                "objectFit": "fill",
                "backgroundPosition": "0% 0%"
              },
              "childCount": 6,
              "children": [
                {
                  "tag": "div",
                  "classes": "swiper-slide swiper-slide-active",
                  "id": "featured_item_JKjAEC",
                  "styles": {
                    "fontSize": "16px",
                    "fontWeight": "400",
                    "fontFamily": "Avenir, sans-serif",
                    "color": "rgb(35, 31, 32)",
                    "background": "rgba(0, 0, 0, 0) none repeat scroll 0% 0% / auto padding-box border-box",
                    "margin": "0px 30px 0px 0px",
                    "marginRight": "30px",
                    "width": "380px",
                    "height": "142.812px",
                    "display": "block",
                    "flexDirection": "row",
                    "border": "0px none rgb(35, 31, 32)",
                    "overflow": "visible",
                    "position": "relative",
                    "opacity": "1",
                    "transform": "matrix(1, 0, 0, 1, 0, 0)",
                    "transition": "transform",
                    "objectFit": "fill",
                    "backgroundPosition": "0% 0%"
                  },
                  "childCount": 2,
                  "children": [
                    {
                      "tag": "style",
                      "classes": "",
                      "text": "[id=\"featured_item_JKjAEC\"] .newBannerSwiperItemText {\n                                font-size: 16px;\n                            }",
                      "styles": {
                        "fontSize": "16px",
                        "fontWeight": "400",
                        "fontFamily": "Avenir, sans-serif",
                        "color": "rgb(35, 31, 32)",
                        "background": "rgba(0, 0, 0, 0) none repeat scroll 0% 0% / auto padding-box border-box",
                        "flexDirection": "row",
                        "border": "0px none rgb(35, 31, 32)",
                        "overflow": "visible",
                        "position": "static",
                        "opacity": "1",
                        "transition": "all",
                        "objectFit": "fill",
                        "backgroundPosition": "0% 0%"
                      },
                      "childCount": 0,
                      "children": []
                    },
                    {
                      "tag": "div",
                      "classes": "newBannerSwiperItem",
                      "styles": {
                        "fontSize": "16px",
                        "fontWeight": "400",
                        "fontFamily": "Avenir, sans-serif",
                        "color": "rgb(35, 31, 32)",
                        "background": "rgba(0, 0, 0, 0) none repeat scroll 0% 0% / auto padding-box border-box",
                        "width": "380px",
                        "height": "142.812px",
                        "display": "flex",
                        "flexDirection": "column",
                        "justifyContent": "space-between",
                        "alignItems": "center",
                        "gap": "34px",
                        "border": "0px none rgb(35, 31, 32)",
                        "overflow": "visible",
                        "position": "static",
                        "opacity": "1",
                        "transition": "all",
                        "objectFit": "fill",
                        "backgroundPosition": "0% 0%"
                      },
                      "childCount": 2,
                      "children": []
                    }
                  ]
                },
                {
                  "tag": "div",
                  "classes": "swiper-slide swiper-slide-next",
                  "id": "featured_item_3QjQWK",
                  "styles": {
                    "fontSize": "16px",
                    "fontWeight": "400",
                    "fontFamily": "Avenir, sans-serif",
                    "color": "rgb(35, 31, 32)",
                    "background": "rgba(0, 0, 0, 0) none repeat scroll 0% 0% / auto padding-box border-box",
                    "margin": "0px 30px 0px 0px",
                    "marginRight": "30px",
                    "width": "380px",
                    "height": "142.812px",
                    "display": "block",
                    "flexDirection": "row",
                    "border": "0px none rgb(35, 31, 32)",
                    "overflow": "visible",
                    "position": "relative",
                    "opacity": "1",
                    "transform": "matrix(1, 0, 0, 1, 0, 0)",
                    "transition": "transform",
                    "objectFit": "fill",
                    "backgroundPosition": "0% 0%"
                  },
                  "childCount": 2,
                  "children": [
                    {
                      "tag": "style",
                      "classes": "",
                      "text": "[id=\"featured_item_3QjQWK\"] .newBannerSwiperItemText {\n                                font-size: 16px;\n                            }",
                      "styles": {
                        "fontSize": "16px",
                        "fontWeight": "400",
                        "fontFamily": "Avenir, sans-serif",
                        "color": "rgb(35, 31, 32)",
                        "background": "rgba(0, 0, 0, 0) none repeat scroll 0% 0% / auto padding-box border-box",
                        "flexDirection": "row",
                        "border": "0px none rgb(35, 31, 32)",
                        "overflow": "visible",
                        "position": "static",
                        "opacity": "1",
                        "transition": "all",
                        "objectFit": "fill",
                        "backgroundPosition": "0% 0%"
                      },
                      "childCount": 0,
                      "children": []
                    },
                    {
                      "tag": "div",
                      "classes": "newBannerSwiperItem",
                      "styles": {
                        "fontSize": "16px",
                        "fontWeight": "400",
                        "fontFamily": "Avenir, sans-serif",
                        "color": "rgb(35, 31, 32)",
                        "background": "rgba(0, 0, 0, 0) none repeat scroll 0% 0% / auto padding-box border-box",
                        "width": "380px",
                        "height": "142.812px",
                        "display": "flex",
                        "flexDirection": "column",
                        "justifyContent": "space-between",
                        "alignItems": "center",
                        "gap": "34px",
                        "border": "0px none rgb(35, 31, 32)",
                        "overflow": "visible",
                        "position": "static",
                        "opacity": "1",
                        "transition": "all",
                        "objectFit": "fill",
                        "backgroundPosition": "0% 0%"
                      },
                      "childCount": 2,
                      "children": []
                    }
                  ]
                },
                {
                  "tag": "div",
                  "classes": "swiper-slide",
                  "id": "featured_item_JQ9HB8",
                  "styles": {
                    "fontSize": "16px",
                    "fontWeight": "400",
                    "fontFamily": "Avenir, sans-serif",
                    "color": "rgb(35, 31, 32)",
                    "background": "rgba(0, 0, 0, 0) none repeat scroll 0% 0% / auto padding-box border-box",
                    "margin": "0px 30px 0px 0px",
                    "marginRight": "30px",
                    "width": "380px",
                    "height": "123.609px",
                    "display": "block",
                    "flexDirection": "row",
                    "border": "0px none rgb(35, 31, 32)",
                    "overflow": "visible",
                    "position": "relative",
                    "opacity": "1",
                    "transform": "matrix(1, 0, 0, 1, 0, 0)",
                    "transition": "transform",
                    "objectFit": "fill",
                    "backgroundPosition": "0% 0%"
                  },
                  "childCount": 2,
                  "children": [
                    {
                      "tag": "style",
                      "classes": "",
                      "text": "[id=\"featured_item_JQ9HB8\"] .newBannerSwiperItemText {\n                                font-size: 16px;\n                            }",
                      "styles": {
                        "fontSize": "16px",
                        "fontWeight": "400",
                        "fontFamily": "Avenir, sans-serif",
                        "color": "rgb(35, 31, 32)",
                        "background": "rgba(0, 0, 0, 0) none repeat scroll 0% 0% / auto padding-box border-box",
                        "flexDirection": "row",
                        "border": "0px none rgb(35, 31, 32)",
                        "overflow": "visible",
                        "position": "static",
                        "opacity": "1",
                        "transition": "all",
                        "objectFit": "fill",
                        "backgroundPosition": "0% 0%"
                      },
                      "childCount": 0,
                      "children": []
                    },
                    {
                      "tag": "div",
                      "classes": "newBannerSwiperItem",
                      "styles": {
                        "fontSize": "16px",
                        "fontWeight": "400",
                        "fontFamily": "Avenir, sans-serif",
                        "color": "rgb(35, 31, 32)",
                        "background": "rgba(0, 0, 0, 0) none repeat scroll 0% 0% / auto padding-box border-box",
                        "width": "380px",
                        "height": "123.609px",
                        "display": "flex",
                        "flexDirection": "column",
                        "justifyContent": "space-between",
                        "alignItems": "center",
                        "gap": "34px",
                        "border": "0px none rgb(35, 31, 32)",
                        "overflow": "visible",
                        "position": "static",
                        "opacity": "1",
                        "transition": "all",
                        "objectFit": "fill",
                        "backgroundPosition": "0% 0%"
                      },
                      "childCount": 2,
                      "children": []
                    }
                  ]
                },
                {
                  "tag": "div",
                  "classes": "swiper-slide",
                  "id": "featured_item_xFabwg",
                  "styles": {
                    "fontSize": "16px",
                    "fontWeight": "400",
                    "fontFamily": "Avenir, sans-serif",
                    "color": "rgb(35, 31, 32)",
                    "background": "rgba(0, 0, 0, 0) none repeat scroll 0% 0% / auto padding-box border-box",
                    "margin": "0px 30px 0px 0px",
                    "marginRight": "30px",
                    "width": "380px",
                    "height": "200.422px",
                    "display": "block",
                    "flexDirection": "row",
                    "border": "0px none rgb(35, 31, 32)",
                    "overflow": "visible",
                    "position": "relative",
                    "opacity": "1",
                    "transform": "matrix(1, 0, 0, 1, 0, 0)",
                    "transition": "transform",
                    "objectFit": "fill",
                    "backgroundPosition": "0% 0%"
                  },
                  "childCount": 2,
                  "children": [
                    {
                      "tag": "style",
                      "classes": "",
                      "text": "[id=\"featured_item_xFabwg\"] .newBannerSwiperItemText {\n                                font-size: 16px;\n                            }",
                      "styles": {
                        "fontSize": "16px",
                        "fontWeight": "400",
                        "fontFamily": "Avenir, sans-serif",
                        "color": "rgb(35, 31, 32)",
                        "background": "rgba(0, 0, 0, 0) none repeat scroll 0% 0% / auto padding-box border-box",
                        "flexDirection": "row",
                        "border": "0px none rgb(35, 31, 32)",
                        "overflow": "visible",
                        "position": "static",
                        "opacity": "1",
                        "transition": "all",
                        "objectFit": "fill",
                        "backgroundPosition": "0% 0%"
                      },
                      "childCount": 0,
                      "children": []
                    },
                    {
                      "tag": "div",
                      "classes": "newBannerSwiperItem",
                      "styles": {
                        "fontSize": "16px",
                        "fontWeight": "400",
                        "fontFamily": "Avenir, sans-serif",
                        "color": "rgb(35, 31, 32)",
                        "background": "rgba(0, 0, 0, 0) none repeat scroll 0% 0% / auto padding-box border-box",
                        "width": "380px",
                        "height": "200.422px",
                        "display": "flex",
                        "flexDirection": "column",
                        "justifyContent": "space-between",
                        "alignItems": "center",
                        "gap": "34px",
                        "border": "0px none rgb(35, 31, 32)",
                        "overflow": "visible",
                        "position": "static",
                        "opacity": "1",
                        "transition": "all",
                        "objectFit": "fill",
                        "backgroundPosition": "0% 0%"
                      },
                      "childCount": 2,
                      "children": []
                    }
                  ]
                },
                {
                  "tag": "div",
                  "classes": "swiper-slide",
                  "id": "featured_item_Q9n3fG",
                  "styles": {
                    "fontSize": "16px",
                    "fontWeight": "400",
                    "fontFamily": "Avenir, sans-serif",
                    "color": "rgb(35, 31, 32)",
                    "background": "rgba(0, 0, 0, 0) none repeat scroll 0% 0% / auto padding-box border-box",
                    "margin": "0px 30px 0px 0px",
                    "marginRight": "30px",
                    "width": "380px",
                    "height": "85.2031px",
                    "display": "block",
                    "flexDirection": "row",
                    "border": "0px none rgb(35, 31, 32)",
                    "overflow": "visible",
                    "position": "relative",
                    "opacity": "1",
                    "transform": "matrix(1, 0, 0, 1, 0, 0)",
                    "transition": "transform",
                    "objectFit": "fill",
                    "backgroundPosition": "0% 0%"
                  },
                  "childCount": 2,
                  "children": [
                    {
                      "tag": "style",
                      "classes": "",
                      "text": "[id=\"featured_item_Q9n3fG\"] .newBannerSwiperItemText {\n                                font-size: 16px;\n                            }",
                      "styles": {
                        "fontSize": "16px",
                        "fontWeight": "400",
                        "fontFamily": "Avenir, sans-serif",
                        "color": "rgb(35, 31, 32)",
                        "background": "rgba(0, 0, 0, 0) none repeat scroll 0% 0% / auto padding-box border-box",
                        "flexDirection": "row",
                        "border": "0px none rgb(35, 31, 32)",
                        "overflow": "visible",
                        "position": "static",
                        "opacity": "1",
                        "transition": "all",
                        "objectFit": "fill",
                        "backgroundPosition": "0% 0%"
                      },
                      "childCount": 0,
                      "children": []
                    },
                    {
                      "tag": "div",
                      "classes": "newBannerSwiperItem",
                      "styles": {
                        "fontSize": "16px",
                        "fontWeight": "400",
                        "fontFamily": "Avenir, sans-serif",
                        "color": "rgb(35, 31, 32)",
                        "background": "rgba(0, 0, 0, 0) none repeat scroll 0% 0% / auto padding-box border-box",
                        "width": "380px",
                        "height": "85.2031px",
                        "display": "flex",
                        "flexDirection": "column",
                        "justifyContent": "space-between",
                        "alignItems": "center",
                        "gap": "34px",
                        "border": "0px none rgb(35, 31, 32)",
                        "overflow": "visible",
                        "position": "static",
                        "opacity": "1",
                        "transition": "all",
                        "objectFit": "fill",
                        "backgroundPosition": "0% 0%"
                      },
                      "childCount": 2,
                      "children": []
                    }
                  ]
                },
                {
                  "tag": "div",
                  "classes": "swiper-slide",
                  "id": "featured_item_TPEACi",
                  "styles": {
                    "fontSize": "16px",
                    "fontWeight": "400",
                    "fontFamily": "Avenir, sans-serif",
                    "color": "rgb(35, 31, 32)",
                    "background": "rgba(0, 0, 0, 0) none repeat scroll 0% 0% / auto padding-box border-box",
                    "margin": "0px 30px 0px 0px",
                    "marginRight": "30px",
                    "width": "380px",
                    "height": "93.9688px",
                    "display": "block",
                    "flexDirection": "row",
                    "border": "0px none rgb(35, 31, 32)",
                    "overflow": "visible",
                    "position": "relative",
                    "opacity": "1",
                    "transform": "matrix(1, 0, 0, 1, 0, 0)",
                    "transition": "transform",
                    "objectFit": "fill",
                    "backgroundPosition": "0% 0%"
                  },
                  "childCount": 2,
                  "children": [
                    {
                      "tag": "style",
                      "classes": "",
                      "text": "[id=\"featured_item_TPEACi\"] .newBannerSwiperItemText {\n                                font-size: 16px;\n                            }",
                      "styles": {
                        "fontSize": "16px",
                        "fontWeight": "400",
                        "fontFamily": "Avenir, sans-serif",
                        "color": "rgb(35, 31, 32)",
                        "background": "rgba(0, 0, 0, 0) none repeat scroll 0% 0% / auto padding-box border-box",
                        "flexDirection": "row",
                        "border": "0px none rgb(35, 31, 32)",
                        "overflow": "visible",
                        "position": "static",
                        "opacity": "1",
                        "transition": "all",
                        "objectFit": "fill",
                        "backgroundPosition": "0% 0%"
                      },
                      "childCount": 0,
                      "children": []
                    },
                    {
                      "tag": "div",
                      "classes": "newBannerSwiperItem",
                      "styles": {
                        "fontSize": "16px",
                        "fontWeight": "400",
                        "fontFamily": "Avenir, sans-serif",
                        "color": "rgb(35, 31, 32)",
                        "background": "rgba(0, 0, 0, 0) none repeat scroll 0% 0% / auto padding-box border-box",
                        "width": "380px",
                        "height": "93.9688px",
                        "display": "flex",
                        "flexDirection": "column",
                        "justifyContent": "space-between",
                        "alignItems": "center",
                        "gap": "34px",
                        "border": "0px none rgb(35, 31, 32)",
                        "overflow": "visible",
                        "position": "static",
                        "opacity": "1",
                        "transition": "all",
                        "objectFit": "fill",
                        "backgroundPosition": "0% 0%"
                      },
                      "childCount": 2,
                      "children": []
                    }
                  ]
                }
              ]
            },
            {
              "tag": "div",
              "classes": "swiper-pagination swiper-pagination-clickable swiper-pagination-bullets swiper-pagination-horizontal",
              "styles": {
                "fontSize": "16px",
                "fontWeight": "400",
                "fontFamily": "Avenir, sans-serif",
                "color": "rgb(35, 31, 32)",
                "background": "rgba(0, 0, 0, 0) none repeat scroll 0% 0% / auto padding-box border-box",
                "margin": "25px 552px 0px",
                "marginTop": "25px",
                "marginRight": "552px",
                "marginLeft": "552px",
                "width": "96px",
                "height": "22px",
                "maxWidth": "fit-content",
                "display": "block",
                "flexDirection": "row",
                "border": "0px none rgb(35, 31, 32)",
                "overflow": "visible",
                "position": "relative",
                "zIndex": "10",
                "opacity": "1",
                "transform": "matrix(1, 0, 0, 1, 0, 0)",
                "transition": "opacity 0.3s",
                "objectFit": "fill",
                "backgroundPosition": "0% 0%"
              },
              "childCount": 4,
              "children": [
                {
                  "tag": "span",
                  "classes": "swiper-pagination-bullet swiper-pagination-bullet-active",
                  "styles": {
                    "fontSize": "16px",
                    "fontWeight": "400",
                    "fontFamily": "Avenir, sans-serif",
                    "color": "rgb(35, 31, 32)",
                    "backgroundColor": "rgb(76, 25, 216)",
                    "background": "rgb(76, 25, 216) none repeat scroll 0% 0% / auto padding-box border-box",
                    "margin": "0px 4px",
                    "marginRight": "4px",
                    "marginLeft": "4px",
                    "width": "16px",
                    "height": "16px",
                    "display": "inline-block",
                    "flexDirection": "row",
                    "borderRadius": "50%",
                    "border": "1px solid rgb(76, 25, 216)",
                    "overflow": "visible",
                    "position": "static",
                    "opacity": "1",
                    "transition": "all",
                    "cursor": "pointer",
                    "objectFit": "fill",
                    "backgroundPosition": "0% 0%"
                  },
                  "childCount": 0,
                  "children": []
                },
                {
                  "tag": "span",
                  "classes": "swiper-pagination-bullet",
                  "styles": {
                    "fontSize": "16px",
                    "fontWeight": "400",
                    "fontFamily": "Avenir, sans-serif",
                    "color": "rgb(35, 31, 32)",
                    "background": "rgba(0, 0, 0, 0) none repeat scroll 0% 0% / auto padding-box border-box",
                    "margin": "0px 4px",
                    "marginRight": "4px",
                    "marginLeft": "4px",
                    "width": "16px",
                    "height": "16px",
                    "display": "inline-block",
                    "flexDirection": "row",
                    "borderRadius": "50%",
                    "border": "1px solid rgb(76, 25, 216)",
                    "overflow": "visible",
                    "position": "static",
                    "opacity": "1",
                    "transition": "all",
                    "cursor": "pointer",
                    "objectFit": "fill",
                    "backgroundPosition": "0% 0%"
                  },
                  "childCount": 0,
                  "children": []
                },
                {
                  "tag": "span",
                  "classes": "swiper-pagination-bullet",
                  "styles": {
                    "fontSize": "16px",
                    "fontWeight": "400",
                    "fontFamily": "Avenir, sans-serif",
                    "color": "rgb(35, 31, 32)",
                    "background": "rgba(0, 0, 0, 0) none repeat scroll 0% 0% / auto padding-box border-box",
                    "margin": "0px 4px",
                    "marginRight": "4px",
                    "marginLeft": "4px",
                    "width": "16px",
                    "height": "16px",
                    "display": "inline-block",
                    "flexDirection": "row",
                    "borderRadius": "50%",
                    "border": "1px solid rgb(76, 25, 216)",
                    "overflow": "visible",
                    "position": "static",
                    "opacity": "1",
                    "transition": "all",
                    "cursor": "pointer",
                    "objectFit": "fill",
                    "backgroundPosition": "0% 0%"
                  },
                  "childCount": 0,
                  "children": []
                },
                {
                  "tag": "span",
                  "classes": "swiper-pagination-bullet",
                  "styles": {
                    "fontSize": "16px",
                    "fontWeight": "400",
                    "fontFamily": "Avenir, sans-serif",
                    "color": "rgb(35, 31, 32)",
                    "background": "rgba(0, 0, 0, 0) none repeat scroll 0% 0% / auto padding-box border-box",
                    "margin": "0px 4px",
                    "marginRight": "4px",
                    "marginLeft": "4px",
                    "width": "16px",
                    "height": "16px",
                    "display": "inline-block",
                    "flexDirection": "row",
                    "borderRadius": "50%",
                    "border": "1px solid rgb(76, 25, 216)",
                    "overflow": "visible",
                    "position": "static",
                    "opacity": "1",
                    "transition": "all",
                    "cursor": "pointer",
                    "objectFit": "fill",
                    "backgroundPosition": "0% 0%"
                  },
                  "childCount": 0,
                  "children": []
                }
              ]
            },
            {
              "tag": "div",
              "classes": "swiper-button-prev mobileOnly swiper-button-disabled",
              "styles": {
                "fontSize": "16px",
                "fontWeight": "400",
                "fontFamily": "Avenir, sans-serif",
                "color": "rgb(3, 152, 197)",
                "background": "rgba(0, 0, 0, 0) none repeat scroll 0% 0% / auto padding-box border-box",
                "margin": "-22px 0px 0px",
                "marginTop": "-22px",
                "width": "24px",
                "height": "24px",
                "flexDirection": "row",
                "justifyContent": "center",
                "alignItems": "center",
                "border": "0px none rgb(3, 152, 197)",
                "overflow": "visible",
                "position": "absolute",
                "top": "50%",
                "left": "10px",
                "zIndex": "10",
                "opacity": "0.35",
                "transition": "all",
                "objectFit": "fill",
                "backgroundPosition": "0% 0%"
              },
              "childCount": 0,
              "children": []
            },
            {
              "tag": "div",
              "classes": "swiper-button-next mobileOnly",
              "styles": {
                "fontSize": "16px",
                "fontWeight": "400",
                "fontFamily": "Avenir, sans-serif",
                "color": "rgb(3, 152, 197)",
                "background": "rgba(0, 0, 0, 0) none repeat scroll 0% 0% / auto padding-box border-box",
                "margin": "-22px 0px 0px",
                "marginTop": "-22px",
                "width": "24px",
                "height": "24px",
                "flexDirection": "row",
                "justifyContent": "center",
                "alignItems": "center",
                "border": "0px none rgb(3, 152, 197)",
                "overflow": "visible",
                "position": "absolute",
                "top": "50%",
                "right": "10px",
                "zIndex": "10",
                "opacity": "1",
                "transition": "all",
                "cursor": "pointer",
                "objectFit": "fill",
                "backgroundPosition": "0% 0%"
              },
              "childCount": 0,
              "children": []
            },
            {
              "tag": "span",
              "classes": "swiper-notification",
              "styles": {
                "fontSize": "16px",
                "fontWeight": "400",
                "fontFamily": "Avenir, sans-serif",
                "color": "rgb(35, 31, 32)",
                "background": "rgba(0, 0, 0, 0) none repeat scroll 0% 0% / auto padding-box border-box",
                "display": "block",
                "flexDirection": "row",
                "border": "0px none rgb(35, 31, 32)",
                "overflow": "visible",
                "position": "absolute",
                "right": "1200px",
                "bottom": "247.422px",
                "zIndex": "-1000",
                "opacity": "0",
                "transition": "all",
                "objectFit": "fill",
                "backgroundPosition": "0% 0%"
              },
              "childCount": 0,
              "children": []
            }
          ]
        }
      ]
    }
  ]
}